[
  {
    "rec_id": "ERs1",
    "classes": [],
    "day_of_week": [],
    "moment_of_day": [],
    "need": [],
    "category_id": [],
    "season": [],
    "topic": [],
    "behaviour_id": [],
    "mission": [
      "EM62",
      "EM63",
      "EM64",
      "EM65",
      "EM66",
      "EM1"
    ],
    "objective": [
      "EO1",
      "EO2",
      "EO3"
    ],
    "hapa": [],
    "comb": [
      "Psychological capability"
    ],
    "intervention_type": [
      "Education",
      "Training",
      "Enablement"
    ],
    "type": "resource"
  },
  {
    "rec_id": "ERs2",
    "classes": [],
    "day_of_week": [],
    "moment_of_day": [],
    "need": [],
    "category_id": [],
    "season": [],
    "topic": [],
    "behaviour_id": [],
    "mission": [
      "EM13",
      "EM14",
      "EM15",
      "EM16",
      "EM17",
      "EM18",
      "EM75"
    ],
    "objective": [
      "EO1",
      "EO2",
      "EO3"
    ],
    "hapa": [],
    "comb": [
      "Psychological capability"
    ],
    "intervention_type": [
      "Education",
      "Training",
      "Enablement"
    ],
    "type": "resource"
  },
  {
    "rec_id": "ERs3",
    "classes": [],
    "day_of_week": [],
    "moment_of_day": [],
    "need": [],
    "category_id": [],
    "season": [],
    "topic": [],
    "behaviour_id": [],
    "mission": [
      "EM26",
      "EM27",
      "EM28",
      "EM29",
      "EM30",
      "EM31"
    ],
    "objective": [
      "EO1",
      "EO2",
      "EO3"
    ],
    "hapa": [],
    "comb": [
      "Psychological capability"
    ],
    "intervention_type": [
      "Education",
      "Training",
      "Enablement"
    ],
    "type": "resource"
  },
  {
    "rec_id": "ERs4",
    "classes": [],
    "day_of_week": [],
    "moment_of_day": [],
    "need": [],
    "category_id": [],
    "season": [],
    "topic": [],
    "behaviour_id": [],
    "mission": [
      "EM22",
      "EM23",
      "EM24",
      "EM25"
    ],
    "objective": [
      "EO1",
      "EO2",
      "EO3"
    ],
    "hapa": [],
    "comb": [
      "Psychological capability"
    ],
    "intervention_type": [
      "Education",
      "Training",
      "Enablement"
    ],
    "type": "resource"
  },
  {
    "rec_id": "ERs5",
    "classes": [],
    "day_of_week": [],
    "moment_of_day": [],
    "need": [],
    "category_id": [],
    "season": [],
    "topic": [],
    "behaviour_id": [],
    "mission": [
      "EM3",
      "EM5",
      "EM57"
    ],
    "objective": [
      "EO1",
      "EO4"
    ],
    "hapa": [],
    "comb": [
      "Psychological capability"
    ],
    "intervention_type": [
      "Education",
      "Training",
      "Enablement"
    ],
    "type": "resource"
  },
  {
    "rec_id": "ERs6",
    "classes": [],
    "day_of_week": [],
    "moment_of_day": [],
    "need": [],
    "category_id": [],
    "season": [],
    "topic": [],
    "behaviour_id": [],
    "mission": [
      "EM7",
      "EM8",
      "EM9",
      "EM10",
      "EM11",
      "EM12"
    ],
    "objective": [
      "EO1",
      "EO2"
    ],
    "hapa": [],
    "comb": [
      "Physical opportunity"
    ],
    "intervention_type": [
      "Education",
      "Training",
      "Modelling"
    ],
    "type": "resource"
  },
  {
    "rec_id": "ERs7",
    "classes": [],
    "day_of_week": [],
    "moment_of_day": [],
    "need": [],
    "category_id": [],
    "season": [],
    "topic": [],
    "behaviour_id": [],
    "mission": [
      "EM4",
      "EM6",
      "EM85",
      "EM86"
    ],
    "objective": [
      "EO1",
      "EO2",
      "EO3"
    ],
    "hapa": [],
    "comb": [
      "Psychological capability"
    ],
    "intervention_type": [
      "Education",
      "Training",
      "Enablement"
    ],
    "type": "resource"
  },
  {
    "rec_id": "ERs8",
    "classes": [],
    "day_of_week": [],
    "moment_of_day": [],
    "need": [],
    "category_id": [],
    "season": [],
    "topic": [],
    "behaviour_id": [],
    "mission": [
      "EM32",
      "EM33",
      "EM38",
      "EM39",
      "EM40",
      "EM42",
      "EM43"
    ],
    "objective": [
      "EO2",
      "EO3",
      "EO4"
    ],
    "hapa": [],
    "comb": [
      "Reflective Motivation"
    ],
    "intervention_type": [
      "Education",
      "Enablement"
    ],
    "type": "resource"
  },
  {
    "rec_id": "ERs9",
    "classes": [],
    "day_of_week": [],
    "moment_of_day": [],
    "need": [],
    "category_id": [],
    "season": [],
    "topic": [],
    "behaviour_id": [],
    "mission": [
      "EM47",
      "EM55",
      "EM54",
      "EM57",
      "EM45",
      "EM84"
    ],
    "objective": [
      "EO2",
      "EO4"
    ],
    "hapa": [],
    "comb": [
      "Reflective Motivation"
    ],
    "intervention_type": [
      "Enablement",
      "Modelling",
      "Environmental Restructuring",
      "Education"
    ],
    "type": "resource"
  },
  {
    "rec_id": "ERs10",
    "classes": [],
    "day_of_week": [],
    "moment_of_day": [],
    "need": [],
    "category_id": [],
    "season": [],
    "topic": [],
    "behaviour_id": [],
    "mission": [
      "EM1",
      "EM2",
      "EM3",
      "EM4",
      "EM5",
      "EM58",
      "EM59",
      "EM60",
      "EM61",
      "EM85",
      "EM86"
    ],
    "objective": [
      "EO1",
      "EO3",
      "EO4"
    ],
    "hapa": [],
    "comb": [
      "Reflective Motivation"
    ],
    "intervention_type": [
      "Education",
      "Incentivisation"
    ],
    "type": "resource"
  },
  {
    "rec_id": "ERs11",
    "classes": [],
    "day_of_week": [],
    "moment_of_day": [],
    "need": [],
    "category_id": [],
    "season": [],
    "topic": [],
    "behaviour_id": [],
    "mission": [
      "EM67",
      "EM68",
      "EM69",
      "EM70",
      "EM71",
      "EM72",
      "EM73",
      "EM74",
      "EM75",
      "EM76",
      "EM77",
      "EM78",
      "EM79",
      "EM80",
      "EM81",
      "EM82"
    ],
    "objective": [
      "EO5"
    ],
    "hapa": [],
    "comb": [
      "Psychological capability"
    ],
    "intervention_type": [
      "Education",
      "Training",
      "Environmental Restructuring",
      "Restrictions",
      "Enablement"
    ],
    "type": "resource"
  },
  {
    "rec_id": "ARs1",
    "classes": [],
    "day_of_week": [],
    "moment_of_day": [],
    "need": [],
    "category_id": [],
    "season": [],
    "topic": [],
    "behaviour_id": [],
    "mission": [
      "AM4"
    ],
    "objective": [
      "AO1"
    ],
    "hapa": [],
    "comb": [
      "Physical capability"
    ],
    "intervention_type": [
      "Education",
      "Persuasion"
    ],
    "type": "resource"
  },
  {
    "rec_id": "ARs2",
    "classes": [],
    "day_of_week": [],
    "moment_of_day": [],
    "need": [],
    "category_id": [],
    "season": [],
    "topic": [],
    "behaviour_id": [],
    "mission": [
      "AM4"
    ],
    "objective": [
      "AO1"
    ],
    "hapa": [
      "Intender"
    ],
    "comb": [
      "Social opportunity"
    ],
    "intervention_type": [
      "Education",
      "Training"
    ],
    "type": "resource"
  },
  {
    "rec_id": "ARs3",
    "classes": [],
    "day_of_week": [],
    "moment_of_day": [],
    "need": [],
    "category_id": [],
    "season": [],
    "topic": [],
    "behaviour_id": [],
    "mission": [
      "AM2"
    ],
    "objective": [
      "AO1"
    ],
    "hapa": [
      "Actor"
    ],
    "comb": [
      "Reflective Motivation"
    ],
    "intervention_type": [
      "Education",
      "Training"
    ],
    "type": "resource"
  },
  {
    "rec_id": "ARs4",
    "classes": [],
    "day_of_week": [],
    "moment_of_day": [],
    "need": [],
    "category_id": [],
    "season": [],
    "topic": [],
    "behaviour_id": [],
    "mission": [
      "AM6"
    ],
    "objective": [
      "AO2"
    ],
    "hapa": [
      "Actor"
    ],
    "comb": [
      "Automatic Motivation"
    ],
    "intervention_type": [
      "Education",
      "Training",
      "Enablement"
    ],
    "type": "resource"
  },
  {
    "rec_id": "ARs5",
    "classes": [],
    "day_of_week": [],
    "moment_of_day": [],
    "need": [],
    "category_id": [],
    "season": [],
    "topic": [],
    "behaviour_id": [],
    "mission": [
      "AM2",
      "AM9"
    ],
    "objective": [
      "AO1",
      "AO2"
    ],
    "hapa": [
      "Actor"
    ],
    "comb": [
      "Psychological capability"
    ],
    "intervention_type": [
      "Education",
      "Persuasion",
      "Environmental Restructuring",
      "Enablement"
    ],
    "type": "resource"
  },
  {
    "rec_id": "PRs1",
    "classes": [],
    "day_of_week": [],
    "moment_of_day": [],
    "need": [],
    "category_id": [],
    "season": [],
    "topic": [],
    "behaviour_id": [],
    "mission": [
      "PM1",
      "PM2",
      "PM3"
    ],
    "objective": [],
    "hapa": [],
    "comb": [],
    "intervention_type": [],
    "type": "resource"
  },
  {
    "rec_id": "PRs2",
    "classes": [],
    "day_of_week": [],
    "moment_of_day": [],
    "need": [],
    "category_id": [],
    "season": [],
    "topic": [],
    "behaviour_id": [],
    "mission": [
      "PM7",
      "PM8",
      "PM9"
    ],
    "objective": [],
    "hapa": [],
    "comb": [],
    "intervention_type": [],
    "type": "resource"
  },
  {
    "rec_id": "PRs3",
    "classes": [],
    "day_of_week": [],
    "moment_of_day": [],
    "need": [],
    "category_id": [],
    "season": [],
    "topic": [],
    "behaviour_id": [],
    "mission": [
      "PM13",
      "PM14",
      "PM15"
    ],
    "objective": [],
    "hapa": [],
    "comb": [],
    "intervention_type": [],
    "type": "resource"
  },
  {
    "rec_id": "PRs4",
    "classes": [],
    "day_of_week": [],
    "moment_of_day": [],
    "need": [],
    "category_id": [],
    "season": [],
    "topic": [],
    "behaviour_id": [],
    "mission": [
      "PM18",
      "PM19",
      "PM20",
      "PM21",
      "PM22",
      "PM23"
    ],
    "objective": [],
    "hapa": [],
    "comb": [],
    "intervention_type": [],
    "type": "resource"
  },
  {
    "rec_id": "PRs5",
    "classes": [],
    "day_of_week": [],
    "moment_of_day": [],
    "need": [],
    "category_id": [],
    "season": [],
    "topic": [],
    "behaviour_id": [],
    "mission": [
      "PM24",
      "PM25",
      "PM26",
      "PM27",
      "PM28",
      "PM29"
    ],
    "objective": [],
    "hapa": [],
    "comb": [],
    "intervention_type": [],
    "type": "resource"
  },
  {
    "rec_id": "PRs6",
    "classes": [],
    "day_of_week": [],
    "moment_of_day": [],
    "need": [],
    "category_id": [],
    "season": [],
    "topic": [],
    "behaviour_id": [],
    "mission": [
      "PM45",
      "PM46",
      "PM47",
      "PM48"
    ],
    "objective": [],
    "hapa": [],
    "comb": [],
    "intervention_type": [],
    "type": "resource"
  },
  {
    "rec_id": "PRs7",
    "classes": [],
    "day_of_week": [],
    "moment_of_day": [],
    "need": [],
    "category_id": [],
    "season": [],
    "topic": [],
    "behaviour_id": [],
    "mission": [],
    "objective": [],
    "hapa": [],
    "comb": [],
    "intervention_type": [],
    "type": "resource"
  },
  {
    "rec_id": "NRs1",
    "classes": [],
    "day_of_week": [],
    "moment_of_day": [],
    "need": [],
    "category_id": [],
    "season": [],
    "topic": [],
    "behaviour_id": [],
    "mission": [
      "NM1",
      "NM2",
      "NM3",
      "NM4",
      "NM5",
      "NM6",
      "NM7",
      "NM8",
      "NM9",
      "NM10",
      "NM11",
      "NM12",
      "NM13",
      "NM14",
      "NM15",
      "NM16",
      "NM17",
      "NM18",
      "NM19",
      "NM20",
      "NM21",
      "NM22",
      "NM23",
      "NM24",
      "NM25",
      "NM26",
      "NM27",
      "NM28",
      "NM29",
      "NM30",
      "NM31",
      "NM32",
      "NM33",
      "NM34",
      "NM35",
      "NM36",
      "NM37",
      "NM38",
      "NM39",
      "NM40",
      "NM41",
      "NM42",
      "NM43",
      "NM44",
      "NM45",
      "NM46",
      "NM47",
      "NM48",
      "NM49",
      "NM50",
      "NM51",
      "NM52",
      "NM53",
      "NM54",
      "NM55",
      "NM56",
      "NM57",
      "NM58",
      "NM59",
      "NM60",
      "NM61",
      "NM62",
      "NM63",
      "NM64",
      "NM65",
      "NM66",
      "NM67",
      "NM68",
      "NM69",
      "NM70",
      "NM71",
      "NM72",
      "NM73",
      "NM74",
      "NM75",
      "NM76",
      "NM77",
      "NM78",
      "NM79",
      "NM80",
      "NM81",
      "NM82",
      "NM83",
      "NM84",
      "NM85",
      "NM86",
      "NM87",
      "NM88",
      "NM89",
      "NM90",
      "NM91",
      "NM92"
    ],
    "objective": [
      "NO1",
      "NO2",
      "NO3",
      "NO4",
      "NO5",
      "NO6",
      "NO7",
      "NO8",
      "NO9",
      "NO10"
    ],
    "hapa": [],
    "comb": [],
    "intervention_type": [],
    "type": "resource"
  },
  {
    "rec_id": "NRs2",
    "classes": [],
    "day_of_week": [],
    "moment_of_day": [],
    "need": [],
    "category_id": [],
    "season": [],
    "topic": [],
    "behaviour_id": [],
    "mission": [
      "NM30",
      "NM31",
      "NM32",
      "NM33",
      "NM34"
    ],
    "objective": [
      "NO4"
    ],
    "hapa": [],
    "comb": [],
    "intervention_type": [],
    "type": "resource"
  },
  {
    "rec_id": "NRs3",
    "classes": [],
    "day_of_week": [],
    "moment_of_day": [],
    "need": [],
    "category_id": [],
    "season": [],
    "topic": [],
    "behaviour_id": [],
    "mission": [
      "NM65",
      "NM71",
      "NM66",
      "NM67",
      "NM68",
      "NM69",
      "NM70",
      "NM30",
      "NM31",
      "NM32",
      "NM33",
      "NM34",
      "NM7",
      "NM8",
      "NM9",
      "NM10",
      "NM11",
      "NM12",
      "NM13",
      "NM14",
      "NM15",
      "NM16"
    ],
    "objective": [
      "NO8"
    ],
    "hapa": [],
    "comb": [],
    "intervention_type": [],
    "type": "resource"
  },
  {
    "rec_id": "NRs4",
    "classes": [],
    "day_of_week": [],
    "moment_of_day": [],
    "need": [],
    "category_id": [],
    "season": [],
    "topic": [],
    "behaviour_id": [],
    "mission": [
      "NM1",
      "NM2",
      "NM3",
      "NM4",
      "NM5",
      "NM6",
      "NM7",
      "NM8",
      "NM9",
      "NM10",
      "NM11",
      "NM12",
      "NM13",
      "NM14",
      "NM15",
      "NM16",
      "NM17",
      "NM18",
      "NM19",
      "NM20",
      "NM21",
      "NM22",
      "NM23",
      "NM24",
      "NM25",
      "NM26",
      "NM27",
      "NM28",
      "NM29",
      "NM30",
      "NM31",
      "NM32",
      "NM33",
      "NM34",
      "NM35",
      "NM36",
      "NM37",
      "NM38",
      "NM39",
      "NM40",
      "NM41",
      "NM42",
      "NM43",
      "NM44",
      "NM45",
      "NM46",
      "NM47",
      "NM48",
      "NM49",
      "NM50",
      "NM51",
      "NM52",
      "NM53",
      "NM54",
      "NM55",
      "NM56",
      "NM57",
      "NM58",
      "NM59",
      "NM60",
      "NM61",
      "NM62",
      "NM63",
      "NM64",
      "NM65",
      "NM66",
      "NM67",
      "NM68",
      "NM69",
      "NM70",
      "NM71",
      "NM72",
      "NM73",
      "NM74",
      "NM75",
      "NM76",
      "NM77",
      "NM78",
      "NM79",
      "NM80",
      "NM81",
      "NM82",
      "NM83",
      "NM84",
      "NM85",
      "NM86",
      "NM87",
      "NM88",
      "NM89",
      "NM90",
      "NM91",
      "NM92"
    ],
    "objective": [
      "NO6",
      "NO1",
      "NO2",
      "NO3",
      "NO4",
      "NO5",
      "NO7",
      "NO8",
      "NO9"
    ],
    "hapa": [],
    "comb": [],
    "intervention_type": [],
    "type": "resource"
  },
  {
    "rec_id": "NRs5",
    "classes": [],
    "day_of_week": [],
    "moment_of_day": [],
    "need": [],
    "category_id": [],
    "season": [],
    "topic": [],
    "behaviour_id": [],
    "mission": [],
    "objective": [],
    "hapa": [],
    "comb": [],
    "intervention_type": [],
    "type": "resource"
  },
  {
    "rec_id": "NRs6",
    "classes": [],
    "day_of_week": [],
    "moment_of_day": [],
    "need": [],
    "category_id": [],
    "season": [],
    "topic": [],
    "behaviour_id": [],
    "mission": [
      "NM1",
      "NM2",
      "NM3",
      "NM4",
      "NM5",
      "NM6",
      "NM7",
      "NM8",
      "NM9",
      "NM10",
      "NM11",
      "NM12",
      "NM13",
      "NM14",
      "NM15",
      "NM16",
      "NM17",
      "NM18",
      "NM19",
      "NM20",
      "NM21",
      "NM22",
      "NM23",
      "NM24",
      "NM25",
      "NM26",
      "NM27",
      "NM28",
      "NM29",
      "NM30",
      "NM31",
      "NM32",
      "NM33",
      "NM34",
      "NM35",
      "NM36",
      "NM37",
      "NM38",
      "NM39",
      "NM40",
      "NM41",
      "NM42",
      "NM43",
      "NM44",
      "NM45",
      "NM46",
      "NM47",
      "NM48",
      "NM49",
      "NM50",
      "NM51",
      "NM52",
      "NM53",
      "NM54",
      "NM55",
      "NM56",
      "NM57",
      "NM58",
      "NM59",
      "NM60",
      "NM61",
      "NM62",
      "NM63",
      "NM64",
      "NM65",
      "NM66",
      "NM67",
      "NM68",
      "NM69",
      "NM70",
      "NM71",
      "NM72",
      "NM73",
      "NM74",
      "NM75",
      "NM76",
      "NM77",
      "NM78",
      "NM79",
      "NM80",
      "NM81",
      "NM82",
      "NM83",
      "NM84",
      "NM85",
      "NM86",
      "NM87",
      "NM88",
      "NM89",
      "NM90",
      "NM91",
      "NM92"
    ],
    "objective": [
      "NO6",
      "NO1",
      "NO2",
      "NO3",
      "NO4",
      "NO5",
      "NO7",
      "NO8",
      "NO9"
    ],
    "hapa": [],
    "comb": [],
    "intervention_type": [],
    "type": "resource"
  },
  {
    "rec_id": "NRs7",
    "classes": [],
    "day_of_week": [],
    "moment_of_day": [],
    "need": [],
    "category_id": [],
    "season": [],
    "topic": [],
    "behaviour_id": [],
    "mission": [
      "NM1",
      "NM2",
      "NM3",
      "NM4",
      "NM5",
      "NM6",
      "NM7",
      "NM8",
      "NM10",
      "NM9",
      "NM11",
      "NM12",
      "NM13",
      "NM14",
      "NM15",
      "NM16"
    ],
    "objective": [
      "NO1",
      "NO2"
    ],
    "hapa": [],
    "comb": [
      "Psychological capability"
    ],
    "intervention_type": [
      "Education",
      "Training"
    ],
    "type": "resource"
  },
  {
    "rec_id": "NRs8",
    "classes": [],
    "day_of_week": [],
    "moment_of_day": [],
    "need": [],
    "category_id": [],
    "season": [],
    "topic": [],
    "behaviour_id": [],
    "mission": [
      "NM1",
      "NM2",
      "NM3",
      "NM4",
      "NM5",
      "NM6",
      "NM7",
      "NM8",
      "NM10",
      "NM9",
      "NM11",
      "NM12",
      "NM13",
      "NM14",
      "NM15",
      "NM16",
      "NM35",
      "NM36",
      "NM37",
      "NM38",
      "NM39"
    ],
    "objective": [
      "NO1",
      "NO2",
      "NO5"
    ],
    "hapa": [],
    "comb": [],
    "intervention_type": [],
    "type": "resource"
  },
  {
    "rec_id": "NRs9",
    "classes": [],
    "day_of_week": [],
    "moment_of_day": [],
    "need": [],
    "category_id": [],
    "season": [],
    "topic": [],
    "behaviour_id": [],
    "mission": [
      "NM79",
      "NM80",
      "NM81",
      "NM82",
      "NM83",
      "NM84",
      "NM85",
      "NM86",
      "NM87",
      "NM88",
      "NM89",
      "NM90",
      "NM91",
      "NM92"
    ],
    "objective": [
      "NO10"
    ],
    "hapa": [],
    "comb": [
      "Psychological capability"
    ],
    "intervention_type": [
      "Education"
    ],
    "type": "resource"
  },
  {
    "rec_id": "SRs1",
    "classes": [],
    "day_of_week": [],
    "moment_of_day": [],
    "need": [],
    "category_id": [],
    "season": [],
    "topic": [],
    "behaviour_id": [],
    "mission": [
      "SM1"
    ],
    "objective": [
      "SO1"
    ],
    "hapa": [
      "Pre-intender"
    ],
    "comb": [
      "Psychological capability"
    ],
    "intervention_type": [
      "Education"
    ],
    "type": "resource"
  },
  {
    "rec_id": "SRs2",
    "classes": [],
    "day_of_week": [],
    "moment_of_day": [],
    "need": [],
    "category_id": [],
    "season": [],
    "topic": [],
    "behaviour_id": [],
    "mission": [
      "SM1"
    ],
    "objective": [
      "SO1"
    ],
    "hapa": [
      "Pre-intender"
    ],
    "comb": [
      "Psychological capability"
    ],
    "intervention_type": [
      "Education"
    ],
    "type": "resource"
  },
  {
    "rec_id": "SRs3",
    "classes": [],
    "day_of_week": [],
    "moment_of_day": [],
    "need": [],
    "category_id": [],
    "season": [],
    "topic": [],
    "behaviour_id": [],
    "mission": [
      "SM2",
      "SM15"
    ],
    "objective": [
      "SO1",
      "SO2"
    ],
    "hapa": [
      "Pre-intender",
      "Intender"
    ],
    "comb": [],
    "intervention_type": [
      "Education"
    ],
    "type": "resource"
  },
  {
    "rec_id": "SRs4",
    "classes": [],
    "day_of_week": [],
    "moment_of_day": [],
    "need": [],
    "category_id": [],
    "season": [],
    "topic": [],
    "behaviour_id": [],
    "mission": [
      "SM16"
    ],
    "objective": [
      "SO1"
    ],
    "hapa": [],
    "comb": [
      "Psychological capability"
    ],
    "intervention_type": [
      "Education",
      "Persuasion",
      "Training",
      "Enablement"
    ],
    "type": "resource"
  },
  {
    "rec_id": "SRs5",
    "classes": [],
    "day_of_week": [],
    "moment_of_day": [],
    "need": [],
    "category_id": [],
    "season": [],
    "topic": [],
    "behaviour_id": [],
    "mission": [
      "SM8"
    ],
    "objective": [
      "SO2"
    ],
    "hapa": [
      "Intender"
    ],
    "comb": [],
    "intervention_type": [
      "Education",
      "Training",
      "Enablement"
    ],
    "type": "resource"
  }
]